{
  "main": [
    {
      "name": "خانه",
      "url": "/"
    },
    {
      "name": "بلاگ",
      "url": "/blogs"
    },
    {
      "name": "محصولات",
      "url": "/pricing"
    },
    {
      "name": "تماس با ما",
      "url": "/contact"
    },
    {
      "name": "سوالات متداول",
      "url": "/faq"
    }
  ],
  "footer": [
    {
      "name": "نارون",
      "menu": [
        {
          "text": "محصولات",
          "url": "/pricing"
        },
        {
          "text": "تماس با ما",
          "url": "#"
        }
      ]
    },
    {
      "name": "Product",
      "menu": [
        {
          "text": "Features",
          "url": "#"
        },
        {
          "text": "Platform",
          "url": "#"
        },
        {
          "text": "Pricing",
          "url": "/pricing"
        }
      ]
    },
    {
      "name": "پشتیبانی",
      "menu": [
        {
          "text": "سوالات متداول",
          "url": "/faq"
        },
        {
          "text": "شرایط و قوانین",
          "url": "#"
        },
        {
          "text": "Terms",
          "url": "#"
        }
      ]
    }
  ]
}
