{
  "facebook": "",
  "twitter": "",
  "instagram": "",
  "youtube": "",
  "linkedin": "",
  "github": "",
  "gitlab": "",
  "discord": "",
  "slack": "",
  "medium": "",
  "codepen": "",
  "bitbucket": "",
  "dribbble": "",
  "behance": "",
  "pinterest": "",
  "soundcloud": "",
  "tumblr": "",
  "reddit": "",
  "vk": "",
  "whatsapp": "+989306057083",
  "telegram": "+989306057083",
  "snapchat": "",
  "vimeo": "",
  "tiktok": "",
  "foursquare": "",
  "rss": "",
  "email": "info@nec.co.ir",
  "phone": "",
  "address": "",
  "skype": "",
  "website": ""
}
